acceso_x402/__init__.py
acceso_x402/client.py
acceso_x402/types.py
acceso_x402/utils.py
acceso_x402-1.0.0.dist-info/licenses/LICENSE
acceso_x402-1.0.0.dist-info/METADATA
acceso_x402-1.0.0.dist-info/WHEEL
acceso_x402-1.0.0.dist-info/top_level.txt
acceso_x402-1.0.0.dist-info/RECORD
