Metadata-Version: 2.4
Name: acceso-x402
Version: 1.0.0
Summary: Python SDK for x402 HTTP payment protocol on Solana
Home-page: https://github.com/acceso-dev/acceso-x402-python
Author: Acceso
Author-email: Acceso <dev@acceso.dev>
License: MIT
Project-URL: Homepage, https://acceso.dev
Project-URL: Documentation, https://docs.acceso.dev
Project-URL: Repository, https://github.com/acceso-dev/acceso-x402-python
Project-URL: Issues, https://github.com/acceso-dev/acceso-x402-python/issues
Keywords: solana,payments,x402,usdc,web3,crypto,blockchain,api,monetization
Classifier: Development Status :: 4 - Beta
Classifier: Intended Audience :: Developers
Classifier: License :: OSI Approved :: MIT License
Classifier: Operating System :: OS Independent
Classifier: Programming Language :: Python :: 3
Classifier: Programming Language :: Python :: 3.8
Classifier: Programming Language :: Python :: 3.9
Classifier: Programming Language :: Python :: 3.10
Classifier: Programming Language :: Python :: 3.11
Classifier: Programming Language :: Python :: 3.12
Classifier: Topic :: Software Development :: Libraries :: Python Modules
Classifier: Topic :: Internet :: WWW/HTTP
Classifier: Topic :: Office/Business :: Financial
Requires-Python: >=3.8
License-File: LICENSE
Requires-Dist: requests>=2.28.0
Requires-Dist: typing-extensions>=4.0.0; python_version < "3.10"
Provides-Extra: dev
Requires-Dist: pytest>=7.0.0; extra == "dev"
Requires-Dist: pytest-cov>=4.0.0; extra == "dev"
Requires-Dist: black>=23.0.0; extra == "dev"
Requires-Dist: isort>=5.12.0; extra == "dev"
Requires-Dist: mypy>=1.0.0; extra == "dev"
Requires-Dist: types-requests>=2.28.0; extra == "dev"
Dynamic: author
Dynamic: home-page
Dynamic: license-file
Dynamic: requires-python
